xmsextractor/__init__.py
xmsextractor/_xmsextractor.cp36-win_amd64.pyd
xmsextractor/extractor/__init__.py
xmsextractor/extractor/ugrid_2d_data_extractor.py
xmsextractor/extractor/ugrid_2d_polyline_data_extractor.py
xmsextractor-3.0.0.dist-info/METADATA
xmsextractor-3.0.0.dist-info/WHEEL
xmsextractor-3.0.0.dist-info/top_level.txt
xmsextractor-3.0.0.dist-info/RECORD
