Metadata-Version: 2.1
Name: xmsextractor
Version: 3.0.0
Summary: UNKNOWN
Home-page: UNKNOWN
Author: Aquaveo
License: BSD 2-Clause License
Platform: UNKNOWN
Requires-Python: ==3.6.*
Requires-Dist: numpy
Requires-Dist: xmscore
Requires-Dist: xmsgrid
